accelbyte_py_sdk/api/ugc/__init__.py
accelbyte_py_sdk/api/ugc/errors.py
accelbyte_py_sdk/api/ugc/models/__init__.py
accelbyte_py_sdk/api/ugc/models/models_add_download_count_response.py
accelbyte_py_sdk/api/ugc/models/models_admin_content_request_v2.py
accelbyte_py_sdk/api/ugc/models/models_admin_get_content_bulk_request.py
accelbyte_py_sdk/api/ugc/models/models_admin_update_content_request.py
accelbyte_py_sdk/api/ugc/models/models_admin_update_content_request_v2.py
accelbyte_py_sdk/api/ugc/models/models_approve_staging_content_request.py
accelbyte_py_sdk/api/ugc/models/models_channel_request.py
accelbyte_py_sdk/api/ugc/models/models_channel_response.py
accelbyte_py_sdk/api/ugc/models/models_config_response.py
accelbyte_py_sdk/api/ugc/models/models_content_download_response.py
accelbyte_py_sdk/api/ugc/models/models_content_download_response_v2.py
accelbyte_py_sdk/api/ugc/models/models_content_downloader_response.py
accelbyte_py_sdk/api/ugc/models/models_content_like_request.py
accelbyte_py_sdk/api/ugc/models/models_content_like_response.py
accelbyte_py_sdk/api/ugc/models/models_content_likers_response.py
accelbyte_py_sdk/api/ugc/models/models_content_request_v2.py
accelbyte_py_sdk/api/ugc/models/models_content_snapshot.py
accelbyte_py_sdk/api/ugc/models/models_content_version_response.py
accelbyte_py_sdk/api/ugc/models/models_copy_content_request.py
accelbyte_py_sdk/api/ugc/models/models_create_content_request.py
accelbyte_py_sdk/api/ugc/models/models_create_content_request_s3.py
accelbyte_py_sdk/api/ugc/models/models_create_content_response.py
accelbyte_py_sdk/api/ugc/models/models_create_content_response_v2.py
accelbyte_py_sdk/api/ugc/models/models_create_group_request.py
accelbyte_py_sdk/api/ugc/models/models_create_group_response.py
accelbyte_py_sdk/api/ugc/models/models_create_screenshot_request.py
accelbyte_py_sdk/api/ugc/models/models_create_screenshot_request_item.py
accelbyte_py_sdk/api/ugc/models/models_create_screenshot_response.py
accelbyte_py_sdk_service_ugc-0.24.0.dist-info/METADATA
accelbyte_py_sdk_service_ugc-0.24.0.dist-info/WHEEL
accelbyte_py_sdk_service_ugc-0.24.0.dist-info/top_level.txt
accelbyte_py_sdk_service_ugc-0.24.0.dist-info/RECORD
